kgc/__init__.py
kgc/__main__.py
kgc/__version__.py
kgc-0.0.3.dist-info/LICENSE
kgc-0.0.3.dist-info/METADATA
kgc-0.0.3.dist-info/WHEEL
kgc-0.0.3.dist-info/entry_points.txt
kgc-0.0.3.dist-info/top_level.txt
kgc-0.0.3.dist-info/RECORD
